pypostcard/__init__.py
pypostcard/compat.py
pypostcard/serde.py
pypostcard/types.py
pypostcard-0.1.1.dist-info/METADATA
pypostcard-0.1.1.dist-info/WHEEL
pypostcard-0.1.1.dist-info/top_level.txt
pypostcard-0.1.1.dist-info/RECORD
